dal/__init__.py
dal/autocomplete.py
dal/forms.py
dal/forward.py
dal/views.py
dal/widgets.py
dal/static/admin/js/jquery.init.js
dal/static/autocomplete_light/autocomplete.init.js
dal/static/autocomplete_light/jquery.init.js
dal/static/autocomplete_light/jquery.post-setup.js
dal/test/__init__.py
dal/test/case.py
dal/test/stories.py
dal/test/utils.py
dal_contenttypes/__init__.py
dal_contenttypes/fields.py
dal_genericm2m/__init__.py
dal_genericm2m/fields.py
dal_genericm2m_queryset_sequence/__init__.py
dal_genericm2m_queryset_sequence/fields.py
dal_gm2m/__init__.py
dal_gm2m/fields.py
dal_gm2m_queryset_sequence/__init__.py
dal_gm2m_queryset_sequence/fields.py
dal_queryset_sequence/__init__.py
dal_queryset_sequence/fields.py
dal_queryset_sequence/views.py
dal_queryset_sequence/widgets.py
dal_queryset_sequence/tests/test_views.py
dal_select2/__init__.py
dal_select2/apps.py
dal_select2/checks.py
dal_select2/fields.py
dal_select2/models.py
dal_select2/test.py
dal_select2/views.py
dal_select2/widgets.py
dal_select2/locale/bg/LC_MESSAGES/django.mo
dal_select2/locale/bg/LC_MESSAGES/django.po
dal_select2/locale/cs/LC_MESSAGES/django.mo
dal_select2/locale/cs/LC_MESSAGES/django.po
dal_select2/locale/de/LC_MESSAGES/django.mo
dal_select2/locale/de/LC_MESSAGES/django.po
dal_select2/locale/es/LC_MESSAGES/django.mo
dal_select2/locale/es/LC_MESSAGES/django.po
dal_select2/locale/fr/LC_MESSAGES/django.mo
dal_select2/locale/fr/LC_MESSAGES/django.po
dal_select2/locale/it/LC_MESSAGES/django.mo
dal_select2/locale/it/LC_MESSAGES/django.po
dal_select2/locale/ja/LC_MESSAGES/django.mo
dal_select2/locale/ja/LC_MESSAGES/django.po
dal_select2/locale/nl/LC_MESSAGES/django.mo
dal_select2/locale/nl/LC_MESSAGES/django.po
dal_select2/locale/pl/LC_MESSAGES/django.mo
dal_select2/locale/pl/LC_MESSAGES/django.po
dal_select2/locale/ru/LC_MESSAGES/django.mo
dal_select2/locale/ru/LC_MESSAGES/django.po
dal_select2/locale/uk/LC_MESSAGES/django.mo
django_autocomplete_light_dj1_compat-3.2.11.dist-info/METADATA
django_autocomplete_light_dj1_compat-3.2.11.dist-info/RECORD
django_autocomplete_light_dj1_compat-3.2.11.dist-info/WHEEL
django_autocomplete_light_dj1_compat-3.2.11.dist-info/top_level.txt
